poshmarkfilter/__init__.py
poshmarkfilter/config.py
poshmarkfilter/filter.py
poshmarkfilter/helpers.py
poshmarkfilter/listing.py
poshmarkfilter/openai.py
poshmarkfilter/poshmark.py
poshmarkfilter-0.0.2.dist-info/LICENSE
poshmarkfilter-0.0.2.dist-info/METADATA
poshmarkfilter-0.0.2.dist-info/WHEEL
poshmarkfilter-0.0.2.dist-info/top_level.txt
poshmarkfilter-0.0.2.dist-info/RECORD
