Metadata-Version: 2.2
Name: poshmarkfilter
Version: 0.0.2
Summary: Use AI to create custom filters on Poshmark
Home-page: https://github.com/samuel-poon/poshmarkfilter-py
Requires-Python: >=3.11
License-File: LICENSE
Requires-Dist: requests
Requires-Dist: beautifulsoup4
Requires-Dist: openai
Dynamic: description
Dynamic: description-content-type
Dynamic: home-page
Dynamic: requires-dist
Dynamic: requires-python
Dynamic: summary
